fetch_houston2013/__init__.py
fetch_houston2013/core/_fetch_augsburg.py
fetch_houston2013/core/_fetch_houston2013mmrs.py
fetch_houston2013/core/common.py
fetch_houston2013/core/fetch_houston2013.py
fetch_houston2013/core/fetch_muufl.py
fetch_houston2013/core/fetch_trento.py
fetch_houston2013/torch/common_hsi_dsm_dataset.py
fetch_houston2013/torch/datasets.py
fetch_houston2013/util/fileio.py
fetch_houston2013/util/lbl2rgb.py
fetch_houston2013/util/split_spmatrix.py
fetch_houston2013-0.8.3.dist-info/METADATA
fetch_houston2013-0.8.3.dist-info/WHEEL
fetch_houston2013-0.8.3.dist-info/licenses/LICENSE
fetch_houston2013-0.8.3.dist-info/RECORD
