Metadata-Version: 2.4
Name: fetch-houston2013
Version: 0.8.3
Summary: Download and load Houston 2013 Dataset
Project-URL: Documentation, https://github.com/songyz2023/fetch-houston2013#readme
Project-URL: Issues, https://github.com/songyz2023/fetch-houston2013/issues
Project-URL: Source, https://github.com/songyz2023/fetch-houston2013
Author-email: songyz2023 <songyz2023dlut@outlook.com>
License-Expression: Apache-2.0
License-File: LICENSE
Classifier: Development Status :: 4 - Beta
Classifier: Programming Language :: Python
Classifier: Programming Language :: Python :: 3.9
Classifier: Programming Language :: Python :: 3.10
Classifier: Programming Language :: Python :: 3.11
Classifier: Programming Language :: Python :: 3.12
Classifier: Programming Language :: Python :: 3.13
Classifier: Programming Language :: Python :: Implementation :: CPython
Classifier: Programming Language :: Python :: Implementation :: PyPy
Requires-Python: >=3.9
Requires-Dist: jaxtyping>=0.2.0
Requires-Dist: numpy>=1.24.0
Requires-Dist: rasterio>=1.2.0
Requires-Dist: scikit-image>=0.21.0
Requires-Dist: scipy>=1.10.0
